{"nodes": [{"id": "d_tiago_dev_pdmtextil_src_app_api_admin_config_banco_dados_route_ts", "label": "route.ts", "file_type": "code", "source_file": "D:\\Tiago\\dev\\pdmtextil\\src\\app\\api\\admin\\config\\banco-dados\\route.ts", "source_location": "L1"}, {"id": "banco_dados_route_get", "label": "GET()", "file_type": "code", "source_file": "D:\\Tiago\\dev\\pdmtextil\\src\\app\\api\\admin\\config\\banco-dados\\route.ts", "source_location": "L8"}, {"id": "banco_dados_route_post", "label": "POST()", "file_type": "code", "source_file": "D:\\Tiago\\dev\\pdmtextil\\src\\app\\api\\admin\\config\\banco-dados\\route.ts", "source_location": "L23"}, {"id": "banco_dados_route_put", "label": "PUT()", "file_type": "code", "source_file": "D:\\Tiago\\dev\\pdmtextil\\src\\app\\api\\admin\\config\\banco-dados\\route.ts", "source_location": "L43"}, {"id": "banco_dados_route_delete", "label": "DELETE()", "file_type": "code", "source_file": "D:\\Tiago\\dev\\pdmtextil\\src\\app\\api\\admin\\config\\banco-dados\\route.ts", "source_location": "L74"}], "edges": [{"source": "d_tiago_dev_pdmtextil_src_app_api_admin_config_banco_dados_route_ts", "target": "server", "relation": "imports_from", "context": "import", "confidence": "EXTRACTED", "source_file": "D:\\Tiago\\dev\\pdmtextil\\src\\app\\api\\admin\\config\\banco-dados\\route.ts", "source_location": "L1", "weight": 1.0}, {"source": "d_tiago_dev_pdmtextil_src_app_api_admin_config_banco_dados_route_ts", "target": "next_auth", "relation": "imports_from", "context": "import", "confidence": "EXTRACTED", "source_file": "D:\\Tiago\\dev\\pdmtextil\\src\\app\\api\\admin\\config\\banco-dados\\route.ts", "source_location": "L2", "weight": 1.0}, {"source": "d_tiago_dev_pdmtextil_src_app_api_admin_config_banco_dados_route_ts", "target": "d_tiago_dev_pdmtextil_src_lib_auth_ts", "relation": "imports_from", "context": "import", "confidence": "EXTRACTED", "source_file": "D:\\Tiago\\dev\\pdmtextil\\src\\app\\api\\admin\\config\\banco-dados\\route.ts", "source_location": "L3", "weight": 1.0}, {"source": "d_tiago_dev_pdmtextil_src_app_api_admin_config_banco_dados_route_ts", "target": "lib_auth_authoptions", "relation": "imports", "context": "import", "confidence": "EXTRACTED", "source_file": "D:\\Tiago\\dev\\pdmtextil\\src\\app\\api\\admin\\config\\banco-dados\\route.ts", "source_location": "L3", "weight": 1.0}, {"source": "d_tiago_dev_pdmtextil_src_app_api_admin_config_banco_dados_route_ts", "target": "d_tiago_dev_pdmtextil_src_lib_db_index_ts", "relation": "imports_from", "context": "import", "confidence": "EXTRACTED", "source_file": "D:\\Tiago\\dev\\pdmtextil\\src\\app\\api\\admin\\config\\banco-dados\\route.ts", "source_location": "L4", "weight": 1.0}, {"source": "d_tiago_dev_pdmtextil_src_app_api_admin_config_banco_dados_route_ts", "target": "db_index_db", "relation": "imports", "context": "import", "confidence": "EXTRACTED", "source_file": "D:\\Tiago\\dev\\pdmtextil\\src\\app\\api\\admin\\config\\banco-dados\\route.ts", "source_location": "L4", "weight": 1.0}, {"source": "d_tiago_dev_pdmtextil_src_app_api_admin_config_banco_dados_route_ts", "target": "d_tiago_dev_pdmtextil_src_lib_db_schema_banco_dados_ts", "relation": "imports_from", "context": "import", "confidence": "EXTRACTED", "source_file": "D:\\Tiago\\dev\\pdmtextil\\src\\app\\api\\admin\\config\\banco-dados\\route.ts", "source_location": "L5", "weight": 1.0}, {"source": "d_tiago_dev_pdmtextil_src_app_api_admin_config_banco_dados_route_ts", "target": "schema_banco_dados_bancosdados", "relation": "imports", "context": "import", "confidence": "EXTRACTED", "source_file": "D:\\Tiago\\dev\\pdmtextil\\src\\app\\api\\admin\\config\\banco-dados\\route.ts", "source_location": "L5", "weight": 1.0}, {"source": "d_tiago_dev_pdmtextil_src_app_api_admin_config_banco_dados_route_ts", "target": "drizzle_orm", "relation": "imports_from", "context": "import", "confidence": "EXTRACTED", "source_file": "D:\\Tiago\\dev\\pdmtextil\\src\\app\\api\\admin\\config\\banco-dados\\route.ts", "source_location": "L6", "weight": 1.0}, {"source": "d_tiago_dev_pdmtextil_src_app_api_admin_config_banco_dados_route_ts", "target": "banco_dados_route_get", "relation": "contains", "confidence": "EXTRACTED", "source_file": "D:\\Tiago\\dev\\pdmtextil\\src\\app\\api\\admin\\config\\banco-dados\\route.ts", "source_location": "L8", "weight": 1.0}, {"source": "d_tiago_dev_pdmtextil_src_app_api_admin_config_banco_dados_route_ts", "target": "banco_dados_route_post", "relation": "contains", "confidence": "EXTRACTED", "source_file": "D:\\Tiago\\dev\\pdmtextil\\src\\app\\api\\admin\\config\\banco-dados\\route.ts", "source_location": "L23", "weight": 1.0}, {"source": "d_tiago_dev_pdmtextil_src_app_api_admin_config_banco_dados_route_ts", "target": "banco_dados_route_put", "relation": "contains", "confidence": "EXTRACTED", "source_file": "D:\\Tiago\\dev\\pdmtextil\\src\\app\\api\\admin\\config\\banco-dados\\route.ts", "source_location": "L43", "weight": 1.0}, {"source": "d_tiago_dev_pdmtextil_src_app_api_admin_config_banco_dados_route_ts", "target": "banco_dados_route_delete", "relation": "contains", "confidence": "EXTRACTED", "source_file": "D:\\Tiago\\dev\\pdmtextil\\src\\app\\api\\admin\\config\\banco-dados\\route.ts", "source_location": "L74", "weight": 1.0}], "raw_calls": [{"caller_nid": "banco_dados_route_get", "callee": "getServerSession", "is_member_call": false, "source_file": "D:\\Tiago\\dev\\pdmtextil\\src\\app\\api\\admin\\config\\banco-dados\\route.ts", "source_location": "L10"}, {"caller_nid": "banco_dados_route_get", "callee": "json", "is_member_call": true, "source_file": "D:\\Tiago\\dev\\pdmtextil\\src\\app\\api\\admin\\config\\banco-dados\\route.ts", "source_location": "L12"}, {"caller_nid": "banco_dados_route_get", "callee": "orderBy", "is_member_call": true, "source_file": "D:\\Tiago\\dev\\pdmtextil\\src\\app\\api\\admin\\config\\banco-dados\\route.ts", "source_location": "L15"}, {"caller_nid": "banco_dados_route_get", "callee": "from", "is_member_call": true, "source_file": "D:\\Tiago\\dev\\pdmtextil\\src\\app\\api\\admin\\config\\banco-dados\\route.ts", "source_location": "L15"}, {"caller_nid": "banco_dados_route_get", "callee": "select", "is_member_call": true, "source_file": "D:\\Tiago\\dev\\pdmtextil\\src\\app\\api\\admin\\config\\banco-dados\\route.ts", "source_location": "L15"}, {"caller_nid": "banco_dados_route_get", "callee": "json", "is_member_call": true, "source_file": "D:\\Tiago\\dev\\pdmtextil\\src\\app\\api\\admin\\config\\banco-dados\\route.ts", "source_location": "L16"}, {"caller_nid": "banco_dados_route_get", "callee": "error", "is_member_call": true, "source_file": "D:\\Tiago\\dev\\pdmtextil\\src\\app\\api\\admin\\config\\banco-dados\\route.ts", "source_location": "L18"}, {"caller_nid": "banco_dados_route_get", "callee": "json", "is_member_call": true, "source_file": "D:\\Tiago\\dev\\pdmtextil\\src\\app\\api\\admin\\config\\banco-dados\\route.ts", "source_location": "L19"}, {"caller_nid": "banco_dados_route_post", "callee": "getServerSession", "is_member_call": false, "source_file": "D:\\Tiago\\dev\\pdmtextil\\src\\app\\api\\admin\\config\\banco-dados\\route.ts", "source_location": "L25"}, {"caller_nid": "banco_dados_route_post", "callee": "json", "is_member_call": true, "source_file": "D:\\Tiago\\dev\\pdmtextil\\src\\app\\api\\admin\\config\\banco-dados\\route.ts", "source_location": "L27"}, {"caller_nid": "banco_dados_route_post", "callee": "json", "is_member_call": true, "source_file": "D:\\Tiago\\dev\\pdmtextil\\src\\app\\api\\admin\\config\\banco-dados\\route.ts", "source_location": "L30"}, {"caller_nid": "banco_dados_route_post", "callee": "json", "is_member_call": true, "source_file": "D:\\Tiago\\dev\\pdmtextil\\src\\app\\api\\admin\\config\\banco-dados\\route.ts", "source_location": "L32"}, {"caller_nid": "banco_dados_route_post", "callee": "returning", "is_member_call": true, "source_file": "D:\\Tiago\\dev\\pdmtextil\\src\\app\\api\\admin\\config\\banco-dados\\route.ts", "source_location": "L35"}, {"caller_nid": "banco_dados_route_post", "callee": "values", "is_member_call": true, "source_file": "D:\\Tiago\\dev\\pdmtextil\\src\\app\\api\\admin\\config\\banco-dados\\route.ts", "source_location": "L35"}, {"caller_nid": "banco_dados_route_post", "callee": "insert", "is_member_call": true, "source_file": "D:\\Tiago\\dev\\pdmtextil\\src\\app\\api\\admin\\config\\banco-dados\\route.ts", "source_location": "L35"}, {"caller_nid": "banco_dados_route_post", "callee": "json", "is_member_call": true, "source_file": "D:\\Tiago\\dev\\pdmtextil\\src\\app\\api\\admin\\config\\banco-dados\\route.ts", "source_location": "L36"}, {"caller_nid": "banco_dados_route_post", "callee": "error", "is_member_call": true, "source_file": "D:\\Tiago\\dev\\pdmtextil\\src\\app\\api\\admin\\config\\banco-dados\\route.ts", "source_location": "L38"}, {"caller_nid": "banco_dados_route_post", "callee": "json", "is_member_call": true, "source_file": "D:\\Tiago\\dev\\pdmtextil\\src\\app\\api\\admin\\config\\banco-dados\\route.ts", "source_location": "L39"}, {"caller_nid": "banco_dados_route_put", "callee": "getServerSession", "is_member_call": false, "source_file": "D:\\Tiago\\dev\\pdmtextil\\src\\app\\api\\admin\\config\\banco-dados\\route.ts", "source_location": "L45"}, {"caller_nid": "banco_dados_route_put", "callee": "json", "is_member_call": true, "source_file": "D:\\Tiago\\dev\\pdmtextil\\src\\app\\api\\admin\\config\\banco-dados\\route.ts", "source_location": "L47"}, {"caller_nid": "banco_dados_route_put", "callee": "json", "is_member_call": true, "source_file": "D:\\Tiago\\dev\\pdmtextil\\src\\app\\api\\admin\\config\\banco-dados\\route.ts", "source_location": "L50"}, {"caller_nid": "banco_dados_route_put", "callee": "json", "is_member_call": true, "source_file": "D:\\Tiago\\dev\\pdmtextil\\src\\app\\api\\admin\\config\\banco-dados\\route.ts", "source_location": "L52"}, {"caller_nid": "banco_dados_route_put", "callee": "transaction", "is_member_call": true, "source_file": "D:\\Tiago\\dev\\pdmtextil\\src\\app\\api\\admin\\config\\banco-dados\\route.ts", "source_location": "L55"}, {"caller_nid": "banco_dados_route_put", "callee": "json", "is_member_call": true, "source_file": "D:\\Tiago\\dev\\pdmtextil\\src\\app\\api\\admin\\config\\banco-dados\\route.ts", "source_location": "L67"}, {"caller_nid": "banco_dados_route_put", "callee": "error", "is_member_call": true, "source_file": "D:\\Tiago\\dev\\pdmtextil\\src\\app\\api\\admin\\config\\banco-dados\\route.ts", "source_location": "L69"}, {"caller_nid": "banco_dados_route_put", "callee": "json", "is_member_call": true, "source_file": "D:\\Tiago\\dev\\pdmtextil\\src\\app\\api\\admin\\config\\banco-dados\\route.ts", "source_location": "L70"}, {"caller_nid": "banco_dados_route_delete", "callee": "getServerSession", "is_member_call": false, "source_file": "D:\\Tiago\\dev\\pdmtextil\\src\\app\\api\\admin\\config\\banco-dados\\route.ts", "source_location": "L76"}, {"caller_nid": "banco_dados_route_delete", "callee": "json", "is_member_call": true, "source_file": "D:\\Tiago\\dev\\pdmtextil\\src\\app\\api\\admin\\config\\banco-dados\\route.ts", "source_location": "L78"}, {"caller_nid": "banco_dados_route_delete", "callee": "json", "is_member_call": true, "source_file": "D:\\Tiago\\dev\\pdmtextil\\src\\app\\api\\admin\\config\\banco-dados\\route.ts", "source_location": "L81"}, {"caller_nid": "banco_dados_route_delete", "callee": "json", "is_member_call": true, "source_file": "D:\\Tiago\\dev\\pdmtextil\\src\\app\\api\\admin\\config\\banco-dados\\route.ts", "source_location": "L83"}, {"caller_nid": "banco_dados_route_delete", "callee": "where", "is_member_call": true, "source_file": "D:\\Tiago\\dev\\pdmtextil\\src\\app\\api\\admin\\config\\banco-dados\\route.ts", "source_location": "L86"}, {"caller_nid": "banco_dados_route_delete", "callee": "eq", "is_member_call": false, "source_file": "D:\\Tiago\\dev\\pdmtextil\\src\\app\\api\\admin\\config\\banco-dados\\route.ts", "source_location": "L86"}, {"caller_nid": "banco_dados_route_delete", "callee": "json", "is_member_call": true, "source_file": "D:\\Tiago\\dev\\pdmtextil\\src\\app\\api\\admin\\config\\banco-dados\\route.ts", "source_location": "L87"}, {"caller_nid": "banco_dados_route_delete", "callee": "error", "is_member_call": true, "source_file": "D:\\Tiago\\dev\\pdmtextil\\src\\app\\api\\admin\\config\\banco-dados\\route.ts", "source_location": "L89"}, {"caller_nid": "banco_dados_route_delete", "callee": "json", "is_member_call": true, "source_file": "D:\\Tiago\\dev\\pdmtextil\\src\\app\\api\\admin\\config\\banco-dados\\route.ts", "source_location": "L90"}]}