{"nodes": [{"id": "d_tiago_dev_pdmtextil_src_lib_db_schema_clientes_ts", "label": "clientes.ts", "file_type": "code", "source_file": "D:\\Tiago\\dev\\pdmtextil\\src\\lib\\db\\schema\\clientes.ts", "source_location": "L1"}, {"id": "schema_clientes_clientes", "label": "clientes", "file_type": "code", "source_file": "D:\\Tiago\\dev\\pdmtextil\\src\\lib\\db\\schema\\clientes.ts", "source_location": "L3"}, {"id": "schema_clientes_cliente", "label": "Cliente", "file_type": "code", "source_file": "D:\\Tiago\\dev\\pdmtextil\\src\\lib\\db\\schema\\clientes.ts", "source_location": "L20"}, {"id": "schema_clientes_newcliente", "label": "NewCliente", "file_type": "code", "source_file": "D:\\Tiago\\dev\\pdmtextil\\src\\lib\\db\\schema\\clientes.ts", "source_location": "L21"}], "edges": [{"source": "d_tiago_dev_pdmtextil_src_lib_db_schema_clientes_ts", "target": "pg_core", "relation": "imports_from", "context": "import", "confidence": "EXTRACTED", "source_file": "D:\\Tiago\\dev\\pdmtextil\\src\\lib\\db\\schema\\clientes.ts", "source_location": "L1", "weight": 1.0}, {"source": "d_tiago_dev_pdmtextil_src_lib_db_schema_clientes_ts", "target": "schema_clientes_clientes", "relation": "contains", "confidence": "EXTRACTED", "source_file": "D:\\Tiago\\dev\\pdmtextil\\src\\lib\\db\\schema\\clientes.ts", "source_location": "L3", "weight": 1.0}, {"source": "d_tiago_dev_pdmtextil_src_lib_db_schema_clientes_ts", "target": "schema_clientes_cliente", "relation": "contains", "confidence": "EXTRACTED", "source_file": "D:\\Tiago\\dev\\pdmtextil\\src\\lib\\db\\schema\\clientes.ts", "source_location": "L20", "weight": 1.0}, {"source": "d_tiago_dev_pdmtextil_src_lib_db_schema_clientes_ts", "target": "schema_clientes_newcliente", "relation": "contains", "confidence": "EXTRACTED", "source_file": "D:\\Tiago\\dev\\pdmtextil\\src\\lib\\db\\schema\\clientes.ts", "source_location": "L21", "weight": 1.0}], "raw_calls": []}